{
  "version": "ver.1",
  "J1": [
    {
      "kickoff": "11/9 (日) 19:00",
      "home": "FC町田ゼルビア",
      "away": "FC東京",
      "predictions": [
        {
          "type": "本命",
          "score": "2-0",
          "odds": "8.2倍",
          "class": "favorite"
        },
        {
          "type": "対抗",
          "score": "1-0",
          "odds": "8.2倍",
          "class": "contender"
        },
        {
          "type": "大穴",
          "score": "1-2",
          "odds": "23.7倍",
          "class": "longshot"
        }
      ]
    }
  ],
  "J2": [
    {
      "kickoff": "11/9 (日) 19:00",
      "home": "徳島ヴォルティス",
      "away": "ヴァンフォーレ甲府",
      "predictions": [
        {
          "type": "本命",
          "score": "2-0",
          "odds": "7.4倍",
          "class": "favorite"
        },
        {
          "type": "対抗",
          "score": "1-0",
          "odds": "8.5倍",
          "class": "contender"
        },
        {
          "type": "大穴",
          "score": "0-1",
          "odds": "28.3倍",
          "class": "longshot"
        }
      ]
    },
    {
      "kickoff": "11/9 (日) 19:00",
      "home": "ジェフユナイテッド千葉",
      "away": "藤枝MYFC",
      "predictions": [
        {
          "type": "本命",
          "score": "2-0",
          "odds": "7.4倍",
          "class": "favorite"
        },
        {
          "type": "対抗",
          "score": "1-0",
          "odds": "8.8倍",
          "class": "contender"
        },
        {
          "type": "大穴",
          "score": "0-0",
          "odds": "20.4倍",
          "class": "longshot"
        }
      ]
    },
    {
      "kickoff": "11/9 (日) 19:00",
      "home": "レノファ山口FC",
      "away": "ジュビロ磐田",
      "predictions": [
        {
          "type": "本命",
          "score": "1-1",
          "odds": "7.8倍",
          "class": "favorite"
        },
        {
          "type": "対抗",
          "score": "0-1",
          "odds": "9.0倍",
          "class": "contender"
        },
        {
          "type": "大穴",
          "score": "2-2",
          "odds": "20.6倍",
          "class": "longshot"
        }
      ]
    },
    {
      "kickoff": "11/9 (日) 19:00",
      "home": "水戸ホーリーホック",
      "away": "RB大宮アルディージャ",
      "predictions": [
        {
          "type": "本命",
          "score": "1-0",
          "odds": "7.8倍",
          "class": "favorite"
        },
        {
          "type": "対抗",
          "score": "2-0",
          "odds": "8.2倍",
          "class": "contender"
        },
        {
          "type": "大穴",
          "score": "0-1",
          "odds": "20.5倍",
          "class": "longshot"
        }
      ]
    },
    {
      "kickoff": "11/9 (日) 19:00",
      "home": "ブラウブリッツ秋田",
      "away": "いわきFC",
      "predictions": [
        {
          "type": "本命",
          "score": "1-0",
          "odds": "7.8倍",
          "class": "favorite"
        },
        {
          "type": "対抗",
          "score": "1-1",
          "odds": "9.4倍",
          "class": "contender"
        },
        {
          "type": "大穴",
          "score": "2-2",
          "odds": "23.6倍",
          "class": "longshot"
        }
      ]
    },
    {
      "kickoff": "11/9 (日) 19:00",
      "home": "カターレ富山",
      "away": "サガン鳥栖",
      "predictions": [
        {
          "type": "本命",
          "score": "1-1",
          "odds": "7.7倍",
          "class": "favorite"
        },
        {
          "type": "対抗",
          "score": "1-0",
          "odds": "9.2倍",
          "class": "contender"
        },
        {
          "type": "大穴",
          "score": "2-2",
          "odds": "21.8倍",
          "class": "longshot"
        }
      ]
    },
    {
      "kickoff": "11/9 (日) 19:00",
      "home": "モンテディオ山形",
      "away": "FC今治",
      "predictions": [
        {
          "type": "本命",
          "score": "2-0",
          "odds": "7.9倍",
          "class": "favorite"
        },
        {
          "type": "対抗",
          "score": "1-0",
          "odds": "8.0倍",
          "class": "contender"
        },
        {
          "type": "大穴",
          "score": "0-1",
          "odds": "20.2倍",
          "class": "longshot"
        }
      ]
    }
  ],
  "J3": [
    {
      "kickoff": "11/9 (日) 19:00",
      "home": "高知ユナイテッドSC",
      "away": "松本山雅FC",
      "predictions": [
        {
          "type": "本命",
          "score": "1-0",
          "odds": "8.0倍",
          "class": "favorite"
        },
        {
          "type": "対抗",
          "score": "1-1",
          "odds": "8.8倍",
          "class": "contender"
        },
        {
          "type": "大穴",
          "score": "2-2",
          "odds": "21.8倍",
          "class": "longshot"
        }
      ]
    },
    {
      "kickoff": "11/9 (日) 19:00",
      "home": "栃木SC",
      "away": "鹿児島ユナイテッドFC",
      "predictions": [
        {
          "type": "本命",
          "score": "1-0",
          "odds": "8.1倍",
          "class": "favorite"
        },
        {
          "type": "対抗",
          "score": "1-1",
          "odds": "8.7倍",
          "class": "contender"
        },
        {
          "type": "大穴",
          "score": "2-2",
          "odds": "22.4倍",
          "class": "longshot"
        }
      ]
    },
    {
      "kickoff": "11/9 (日) 19:00",
      "home": "FC琉球",
      "away": "アスルクラロ沼津",
      "predictions": [
        {
          "type": "本命",
          "score": "1-0",
          "odds": "8.1倍",
          "class": "favorite"
        },
        {
          "type": "対抗",
          "score": "2-0",
          "odds": "8.5倍",
          "class": "contender"
        },
        {
          "type": "大穴",
          "score": "4-0",
          "odds": "23.6倍",
          "class": "longshot"
        }
      ]
    },
    {
      "kickoff": "11/9 (日) 19:00",
      "home": "FC岐阜",
      "away": "ガイナーレ鳥取",
      "predictions": [
        {
          "type": "本命",
          "score": "1-0",
          "odds": "7.9倍",
          "class": "favorite"
        },
        {
          "type": "対抗",
          "score": "2-0",
          "odds": "9.0倍",
          "class": "contender"
        },
        {
          "type": "大穴",
          "score": "1-2",
          "odds": "21.8倍",
          "class": "longshot"
        }
      ]
    },
    {
      "kickoff": "11/9 (日) 19:00",
      "home": "ギラヴァンツ北九州",
      "away": "福島ユナイテッドFC",
      "predictions": [
        {
          "type": "本命",
          "score": "1-0",
          "odds": "8.2倍",
          "class": "favorite"
        },
        {
          "type": "対抗",
          "score": "2-0",
          "odds": "9.3倍",
          "class": "contender"
        },
        {
          "type": "大穴",
          "score": "1-2",
          "odds": "21.3倍",
          "class": "longshot"
        }
      ]
    },
    {
      "kickoff": "11/9 (日) 19:00",
      "home": "テゲバジャーロ宮崎",
      "away": "ザスパ群馬",
      "predictions": [
        {
          "type": "本命",
          "score": "2-0",
          "odds": "7.4倍",
          "class": "favorite"
        },
        {
          "type": "対抗",
          "score": "1-0",
          "odds": "8.3倍",
          "class": "contender"
        },
        {
          "type": "大穴",
          "score": "0-0",
          "odds": "20.0倍",
          "class": "longshot"
        }
      ]
    },
    {
      "kickoff": "11/9 (日) 19:00",
      "home": "SC相模原",
      "away": "ツエーゲン金沢",
      "predictions": [
        {
          "type": "本命",
          "score": "1-0",
          "odds": "8.2倍",
          "class": "favorite"
        },
        {
          "type": "対抗",
          "score": "2-0",
          "odds": "8.6倍",
          "class": "contender"
        },
        {
          "type": "大穴",
          "score": "1-2",
          "odds": "21.9倍",
          "class": "longshot"
        }
      ]
    }
  ]
}